regex_spm/__init__.py
regex_spm/regex_spm_match.py
regex_spm-1.0.0.dist-info/LICENSE
regex_spm-1.0.0.dist-info/METADATA
regex_spm-1.0.0.dist-info/WHEEL
regex_spm-1.0.0.dist-info/top_level.txt
regex_spm-1.0.0.dist-info/RECORD
