Metadata-Version: 2.1
Name: regex-spm
Version: 1.0.0
Summary: Enable Structural Pattern Matching for Python regular expressions
Home-page: https://github.com/aronhoff/regex_spm
Author: aronhoffmann
Author-email: aron.m.hoff+pypy@gmail.com
License: MIT
Classifier: Programming Language :: Python :: 3
Classifier: License :: OSI Approved :: MIT License
Classifier: Operating System :: OS Independent
Classifier: Topic :: Software Development :: Libraries :: Python Modules
Requires-Python: >=3.10
License-File: LICENSE
